modelchecks/__init__.py
modelchecks/__version__.py
modelchecks/core.py
modelchecks/utils.py
CoopIHC_ModelChecks-0.1.1.dist-info/LICENSE
CoopIHC_ModelChecks-0.1.1.dist-info/METADATA
CoopIHC_ModelChecks-0.1.1.dist-info/WHEEL
CoopIHC_ModelChecks-0.1.1.dist-info/top_level.txt
CoopIHC_ModelChecks-0.1.1.dist-info/RECORD
