Metadata-Version: 2.1
Name: CoopIHC-ModelChecks
Version: 0.1.1
Summary: User modeling checks for computational HCI using CoopIHC.
Home-page: https://github.com/christophajohns/CoopIHC-ModelChecks
Author: Christoph Johns
Author-email: christoph.johns@aalto.fi
License: MIT
Platform: UNKNOWN
Classifier: License :: OSI Approved :: MIT License
Classifier: Programming Language :: Python
Classifier: Programming Language :: Python :: 3
Classifier: Programming Language :: Python :: 3.6
Classifier: Programming Language :: Python :: Implementation :: CPython
Classifier: Programming Language :: Python :: Implementation :: PyPy
Requires-Python: >=3.6.0
Requires-Dist: numpy
Requires-Dist: pandas
Requires-Dist: scipy
Requires-Dist: tqdm
Requires-Dist: statsmodels
Requires-Dist: tabulate
Requires-Dist: pyro-ppl
Requires-Dist: torch
Provides-Extra: plots
Requires-Dist: matplotlib ; extra == 'plots'
Requires-Dist: seaborn ; extra == 'plots'
